{
  "minecraft:recipes/decorations/crafting_table": {
    "criteria": {
      "unlock_right_away": "2024-07-20 11:59:43 +0000"
    },
    "done": true
  },
  "minecraft:adventure/adventuring_time": {
    "criteria": {
      "minecraft:old_growth_birch_forest": "2024-07-20 11:59:52 +0000",
      "minecraft:ocean": "2024-07-20 13:48:00 +0000",
      "minecraft:meadow": "2024-07-20 11:59:44 +0000"
    },
    "done": false
  },
  "minecraft:adventure/root": {
    "criteria": {
      "killed_by_something": "2024-07-20 13:50:04 +0000"
    },
    "done": true
  },
  "minecraft:husbandry/balanced_diet": {
    "criteria": {
      "golden_carrot": "2024-07-20 13:52:49 +0000"
    },
    "done": false
  },
  "minecraft:husbandry/root": {
    "criteria": {
      "consumed_item": "2024-07-20 13:52:49 +0000"
    },
    "done": true
  },
  "DataVersion": 3953
}